{
    "name": "Icons",
    "description": "",
    "icons": [
        {
            "name": "douban",
            "url": "https://raw.githubusercontent.com/firimar/Quantumult-X/main/Icons/db.png"
        },
        {
            "name": "duitang",
            "url": "https://raw.githubusercontent.com/firimar/Quantumult-X/main/Icons/duitang.png"
        },
        {
            "name": "huaban",
            "url": "https://raw.githubusercontent.com/firimar/Quantumult-X/main/Icons/huaban.png"
        }
    ]
}